LICENSE
README.md
setup.cfg
setup.py
qrdet/__init__.py
qrdet/_qrdet_helpers.py
qrdet/output_qrdet_dict_keys.py
qrdet/qrdet.py
qrdet.egg-info/PKG-INFO
qrdet.egg-info/SOURCES.txt
qrdet.egg-info/dependency_links.txt
qrdet.egg-info/requires.txt
qrdet.egg-info/top_level.txt