Metadata-Version: 2.1
Name: qrdet
Version: 2.4
Summary: Robust QR Detector based on YOLOv8
Home-page: https://github.com/Eric-Canas/qrdet
Author: Eric Canas
Author-email: eric@ericcanas.com
License: MIT
Classifier: Development Status :: 5 - Production/Stable
Classifier: Intended Audience :: Developers
Classifier: Intended Audience :: Science/Research
Classifier: License :: OSI Approved :: MIT License
Classifier: Operating System :: OS Independent
Classifier: Programming Language :: Python :: 3
Classifier: Topic :: Scientific/Engineering :: Image Recognition
Classifier: Topic :: Scientific/Engineering :: Artificial Intelligence
Classifier: Topic :: Software Development :: Libraries :: Python Modules
Classifier: Topic :: Utilities
Classifier: Topic :: Multimedia :: Graphics
Classifier: Typing :: Typed
License-File: LICENSE
